opensea/__init__.py
opensea/opensea.py
opensea/opensea_api.py
opensea/utils.py
opensea_api-0.1.7.dist-info/LICENSE
opensea_api-0.1.7.dist-info/METADATA
opensea_api-0.1.7.dist-info/WHEEL
opensea_api-0.1.7.dist-info/top_level.txt
opensea_api-0.1.7.dist-info/RECORD
