Metadata-Version: 2.1
Name: opensea-api
Version: 0.1.7
Summary: Python 3 wrapper for the OpenSea NFT API
Home-page: https://github.com/zseta/python-opensea
Author: Attila Toth
Author-email: hello@attilatoth.dev
Maintainer: Attila Toth
Maintainer-email: hello@attilatoth.dev
License: MIT license
Project-URL: Documentation, https://opensea-api.attilatoth.dev
Project-URL: Source, https://github.com/zseta/python-opensea
Keywords: opensea,nft,non fungible token,crypto
Platform: UNKNOWN
Classifier: Development Status :: 4 - Beta
Classifier: Intended Audience :: Developers
Classifier: Environment :: Web Environment
Classifier: License :: OSI Approved :: MIT License
Classifier: Natural Language :: English
Classifier: Programming Language :: Python
Classifier: Programming Language :: Python :: 3
Classifier: Programming Language :: Python :: 3.6
Classifier: Programming Language :: Python :: 3.7
Classifier: Programming Language :: Python :: 3.8
Classifier: Topic :: Internet
Classifier: Topic :: Internet :: WWW/HTTP :: HTTP Servers
Classifier: Topic :: Office/Business :: Financial
Classifier: Topic :: Software Development :: Libraries
Classifier: Topic :: Software Development :: Libraries :: Python Modules
Classifier: Topic :: Utilities
Requires-Python: >=3.6
License-File: LICENSE
Requires-Dist: requests (>=2.26.0)
